arrakis_server/__init__.py
arrakis_server/__main__.py
arrakis_server/_version.py
arrakis_server/arrow.py
arrakis_server/channel.py
arrakis_server/constants.py
arrakis_server/errors.py
arrakis_server/metadata.py
arrakis_server/partition.py
arrakis_server/py.typed
arrakis_server/schemas.py
arrakis_server/scope.py
arrakis_server/server.py
arrakis_server/traits.py
arrakis_server/backends/__init__.py
arrakis_server/backends/mock/__init__.py
arrakis_server/backends/mock/channels/H1_channels.toml
arrakis_server/backends/mock/channels/L1_channels.toml
arrakis_server/backends/mock/channels/__init__.py
arrakis_server/tests/__init__.py
arrakis_server/tests/conftest.py
arrakis_server/tests/test_api.py
arrakis_server/tests/test_partition.py
arrakis_server/tests/test_server.py
arrakis_server/tests/data/channels.toml
arrakis_server-0.4.1.dist-info/METADATA
arrakis_server-0.4.1.dist-info/WHEEL
arrakis_server-0.4.1.dist-info/entry_points.txt
arrakis_server-0.4.1.dist-info/licenses/AUTHORS.md
arrakis_server-0.4.1.dist-info/licenses/LICENSE
arrakis_server-0.4.1.dist-info/RECORD
